electricalsystemcalculator/__init__.py
electricalsystemcalculator/three_phase_calculations.py
electricalsystemcalculator-0.1.1.dist-info/LICENSE
electricalsystemcalculator-0.1.1.dist-info/METADATA
electricalsystemcalculator-0.1.1.dist-info/WHEEL
electricalsystemcalculator-0.1.1.dist-info/top_level.txt
electricalsystemcalculator-0.1.1.dist-info/RECORD
