Metadata-Version: 2.1
Name: electricalsystemcalculator
Version: 0.1.1
Summary: A Python library for three-phase electrical system calculations.
Home-page: https://github.com/Modular-Minds/ElectricalSystemCalculator
Author: Bharti Mishra, Madhuri Shriniwar
Author-email: bhartimishra7941@gmail.com, madhurishriniwar24@gmail.com
License: MIT
Project-URL: Documentation, https://github.com/Modular-Minds/ElectricalSystemCalculator#readme
Project-URL: Source, https://github.com/Modular-Minds/ElectricalSystemCalculator
Project-URL: Tracker, https://github.com/Modular-Minds/ElectricalSystemCalculator/issues
Keywords: three-phase,electrical,power system,engineering,calculations
Classifier: Programming Language :: Python :: 3
Classifier: License :: OSI Approved :: MIT License
Classifier: Operating System :: OS Independent
Classifier: Intended Audience :: Science/Research
Classifier: Intended Audience :: Education
Classifier: Topic :: Scientific/Engineering :: Physics
Classifier: Topic :: Scientific/Engineering :: Information Analysis
Requires-Python: >=3.6
License-File: LICENSE
